gate_ws/__init__.py
gate_ws/client.py
gate_ws/futures.py
gate_ws/spot.py
gate_ws-0.3.1.dist-info/METADATA
gate_ws-0.3.1.dist-info/WHEEL
gate_ws-0.3.1.dist-info/top_level.txt
gate_ws-0.3.1.dist-info/RECORD
