Metadata-Version: 2.1
Name: gate-ws
Version: 0.3.1
Summary: Gate.io WebSocket V4 Python SDK
Home-page: https://github.com/gateio/gatews
Author: gateio
Author-email: dev@mail.gate.io
Maintainer: gateio
Maintainer-email: dev@mail.gate.io
License: MIT License
Keywords: Gate WebSocket V4
Platform: UNKNOWN
Classifier: License :: OSI Approved :: MIT License
Classifier: Development Status :: 3 - Alpha
Classifier: Framework :: AsyncIO
Classifier: Programming Language :: Python :: 3
Classifier: Programming Language :: Python :: 3.6
Classifier: Programming Language :: Python :: 3.7
Classifier: Programming Language :: Python :: 3.8
Classifier: Programming Language :: Python :: 3.9
Classifier: Programming Language :: Python :: 3.10
Requires-Dist: websockets (>=8.1)
